{
  "runnableVersion": "01.00.00",
  "name": "runnableUDSName",
  "runnables": [
    {
      "timeout": 3000,
      "name": "uds",
      "subscriptions": [
        {
          "type": "uds",
          "path": "/tmp/unix.sock",
          "name": "udsSubscription",
          "onMessageReceived": "message = JSON.parse(message); test['Message received is {{udsPayload}}'] = message === '{{udsPayload}}';",
          "timeout": 500
        }
      ],
      "startEvent": {
        "publisher": {
          "type": "uds",
          "name": "udsPublisher",
          "path": "/tmp/unix.sock",
          "payload": "{{udsPayload}}",
          "prePublishing": "const payload = 'enqueuer'; persistSessionVariable('udsPayload', payload); persistSessionVariable('uds2RequisitionName', 'RequisitionUds2Name'); persistSessionVariable('uds2Timeout', '500');"
        }
      }
    },
    {
      "name": "{{uds2RequisitionName}}",
      "subscriptions": [
        {
          "type": "uds",
          "path": "/tmp/unix2.sock",
          "name": "udsSubscription2",
          "onMessageReceived": "message = JSON.parse(message); test['Message received is {{udsPayload}}'] = message === '{{udsPayload}}';",
          "timeout": "{{uds2Timeout}}"
        }
      ],
      "startEvent": {
        "publisher": {
          "type": "uds",
          "name": "udsPublisher2",
          "path": "/tmp/unix2.sock",
          "payload": "{{udsPayload}}",
          "prePublishing": "test['Message to be published is {{udsPayload}}'] = publisher.payload === '{{udsPayload}}';"
        }
      }
    }

  ]
}